popgames/__init__.py
popgames/alarm_clock.py
popgames/payoff_mechanism.py
popgames/population_game.py
popgames/revision_process.py
popgames/revision_protocol.py
popgames/simulator.py
popgames/utilities/__init__.py
popgames/utilities/gnep_solvers.py
popgames/utilities/input_validators.py
popgames/utilities/plotters.py
popgames/utilities/polyhedron.py
popgames-0.1.0.dist-info/LICENSE
popgames-0.1.0.dist-info/METADATA
popgames-0.1.0.dist-info/WHEEL
popgames-0.1.0.dist-info/RECORD
